LICENSE
ciff_toolkit/__init__.py
ciff_toolkit/ciff_pb2.py
ciff_toolkit/cli.py
ciff_toolkit/merge.py
ciff_toolkit/protos/ciff.proto
ciff_toolkit/read.py
ciff_toolkit/util.py
ciff_toolkit/write.py
ciff_toolkit-0.1.1.dist-info/entry_points.txt
ciff_toolkit-0.1.1.dist-info/LICENSE
ciff_toolkit-0.1.1.dist-info/WHEEL
ciff_toolkit-0.1.1.dist-info/METADATA
ciff_toolkit-0.1.1.dist-info/RECORD
