Metadata-Version: 2.1
Name: ciff-toolkit
Version: 0.1.1
Summary: Toolkit for working with Common Index File Format (CIFF) files.
Home-page: https://opencode.it4i.eu/openwebsearcheu-public/ciff-toolkit/
License: MIT
Keywords: ciff
Author: Gijs Hendriksen
Author-email: g.hendriksen@cs.ru.nl
Requires-Python: >=3.10,<4.0
Classifier: License :: OSI Approved :: MIT License
Classifier: Operating System :: OS Independent
Classifier: Programming Language :: Python :: 3
Classifier: Programming Language :: Python :: 3.10
Requires-Dist: protobuf (>=4.21.12,<5.0.0)
Requires-Dist: tqdm (>=4.64.1,<5.0.0)
Project-URL: Repository, https://opencode.it4i.eu/openwebsearcheu-public/ciff-toolkit/
